ApexxCloud/ApexxCloud.py
ApexxCloud/__init__.py
apexxcloud-1.0.dist-info/METADATA
apexxcloud-1.0.dist-info/WHEEL
apexxcloud-1.0.dist-info/licenses/LICENSE
apexxcloud-1.0.dist-info/RECORD
