Metadata-Version: 2.4
Name: ApexxCloud
Version: 1.0
Summary: A Python package for ApexxCloud API
Project-URL: Homepage, https://github.com/Anipathy/ApexxCloud_SDK
Author-email: Anirudh <anipathy17@gmail.com>
License-File: LICENSE
Classifier: License :: OSI Approved :: MIT License
Classifier: Operating System :: OS Independent
Classifier: Programming Language :: Python :: 3
Requires-Python: >=3.8
Requires-Dist: aiohttp>=3.8.0
Requires-Dist: pycryptodome>3.9.0
Requires-Dist: requests>2.20.0
